cardmasking/__init__.py
cardmasking/masking.py
cardmasking-0.1.3.dist-info/METADATA
cardmasking-0.1.3.dist-info/WHEEL
cardmasking-0.1.3.dist-info/top_level.txt
cardmasking-0.1.3.dist-info/RECORD
