Metadata-Version: 2.1
Name: cardmasking
Version: 0.1.3
Summary: This is to Mask the Card details
Author: Surya
Author-email: suryatejareddy64@gmail.com
